pipedream/.python-version
pipedream/cache.py
pipedream/director.py
pipedream/engine.py
pipedream/gui.py
pipedream/navigator.py
pipedream/games/mock_game.py
pipedream/ui/main.qml
pipedream_fiction-0.2.3.dist-info/METADATA
pipedream_fiction-0.2.3.dist-info/WHEEL
pipedream_fiction-0.2.3.dist-info/entry_points.txt
pipedream_fiction-0.2.3.dist-info/licenses/LICENSE
pipedream_fiction-0.2.3.dist-info/RECORD
