Metadata-Version: 2.4
Name: pipedream-fiction
Version: 0.2.3
Summary: Real-time generative visualization for interactive fiction.
Author-email: "Pxld Ltd." <charlespritchardwork@gmail.com>
License-File: LICENSE
Requires-Python: >=3.11
Requires-Dist: google-auth>=2.47.0
Requires-Dist: google-generativeai>=0.8.6
Requires-Dist: litellm>=1.80.16
Requires-Dist: opencv-python>=4.12.0.88
Requires-Dist: pexpect>=4.9.0
Requires-Dist: pyside6>=6.10.1
Requires-Dist: python-dotenv>=1.2.1
Requires-Dist: requests>=2.32.5
